{
  "frame_id": 78,
  "timestamp": 1341846229.430182,
  "image_path": "rgb/1341846229.430182.png",
  "detections": [
    {
      "class_id": 0,
      "class_name": "person",
      "confidence": 0.9021,
      "bbox": [
        337.8,
        151.8,
        599.6,
        468.1
      ],
      "is_dynamic": true,
      "mask_bbox_shape": [
        480,
        640
      ]
    },
    {
      "class_id": 0,
      "class_name": "person",
      "confidence": 0.8567,
      "bbox": [
        106.0,
        2.0,
        239.9,
        479.2
      ],
      "is_dynamic": true,
      "mask_bbox_shape": [
        480,
        640
      ]
    },
    {
      "class_id": 62,
      "class_name": "tv",
      "confidence": 0.8457,
      "bbox": [
        354.9,
        155.1,
        480.3,
        245.4
      ],
      "is_dynamic": false,
      "mask_bbox_shape": [
        480,
        640
      ]
    },
    {
      "class_id": 56,
      "class_name": "chair",
      "confidence": 0.7775,
      "bbox": [
        19.0,
        238.0,
        236.6,
        479.7
      ],
      "is_dynamic": false,
      "mask_bbox_shape": [
        480,
        640
      ]
    },
    {
      "class_id": 64,
      "class_name": "mouse",
      "confidence": 0.697,
      "bbox": [
        266.0,
        259.7,
        283.0,
        269.8
      ],
      "is_dynamic": false,
      "mask_bbox_shape": [
        480,
        640
      ]
    },
    {
      "class_id": 62,
      "class_name": "tv",
      "confidence": 0.6181,
      "bbox": [
        207.3,
        165.5,
        264.0,
        236.9
      ],
      "is_dynamic": false,
      "mask_bbox_shape": [
        480,
        640
      ]
    },
    {
      "class_id": 39,
      "class_name": "bottle",
      "confidence": 0.5854,
      "bbox": [
        474.2,
        215.7,
        488.9,
        255.7
      ],
      "is_dynamic": false,
      "mask_bbox_shape": [
        480,
        640
      ]
    }
  ],
  "num_detections": 7,
  "num_dynamic": 2
}