{
  "frame_id": 335,
  "timestamp": 1341846238.109791,
  "image_path": "rgb/1341846238.109791.png",
  "detections": [
    {
      "class_id": 62,
      "class_name": "tv",
      "confidence": 0.8962,
      "bbox": [
        358.9,
        199.1,
        483.3,
        291.7
      ],
      "is_dynamic": false,
      "mask_bbox_shape": [
        480,
        640
      ]
    },
    {
      "class_id": 62,
      "class_name": "tv",
      "confidence": 0.8858,
      "bbox": [
        187.6,
        210.9,
        267.9,
        277.7
      ],
      "is_dynamic": false,
      "mask_bbox_shape": [
        480,
        640
      ]
    },
    {
      "class_id": 56,
      "class_name": "chair",
      "confidence": 0.8818,
      "bbox": [
        113.0,
        298.7,
        253.1,
        479.9
      ],
      "is_dynamic": false,
      "mask_bbox_shape": [
        480,
        640
      ]
    },
    {
      "class_id": 56,
      "class_name": "chair",
      "confidence": 0.845,
      "bbox": [
        413.5,
        331.1,
        594.1,
        479.7
      ],
      "is_dynamic": false,
      "mask_bbox_shape": [
        480,
        640
      ]
    },
    {
      "class_id": 64,
      "class_name": "mouse",
      "confidence": 0.6227,
      "bbox": [
        269.4,
        303.8,
        285.2,
        314.9
      ],
      "is_dynamic": false,
      "mask_bbox_shape": [
        480,
        640
      ]
    },
    {
      "class_id": 66,
      "class_name": "keyboard",
      "confidence": 0.5676,
      "bbox": [
        173.9,
        286.5,
        262.1,
        307.1
      ],
      "is_dynamic": false,
      "mask_bbox_shape": [
        480,
        640
      ]
    },
    {
      "class_id": 0,
      "class_name": "person",
      "confidence": 0.5275,
      "bbox": [
        571.9,
        149.4,
        639.8,
        437.9
      ],
      "is_dynamic": true,
      "mask_bbox_shape": [
        480,
        640
      ]
    },
    {
      "class_id": 39,
      "class_name": "bottle",
      "confidence": 0.5225,
      "bbox": [
        478.7,
        259.3,
        493.0,
        300.3
      ],
      "is_dynamic": false,
      "mask_bbox_shape": [
        480,
        640
      ]
    }
  ],
  "num_detections": 8,
  "num_dynamic": 1
}