{
  "frame_id": 123,
  "timestamp": 123.0,
  "image_path": "image_0/000123.png",
  "detections": [
    {
      "class_id": 2,
      "class_name": "car",
      "confidence": 0.9221,
      "bbox": [
        142.5,
        198.3,
        536.5,
        373.8
      ],
      "is_dynamic": true,
      "mask_bbox_shape": [
        224,
        640
      ]
    },
    {
      "class_id": 2,
      "class_name": "car",
      "confidence": 0.9022,
      "bbox": [
        870.1,
        195.2,
        1240.3,
        371.5
      ],
      "is_dynamic": true,
      "mask_bbox_shape": [
        224,
        640
      ]
    },
    {
      "class_id": 2,
      "class_name": "car",
      "confidence": 0.8128,
      "bbox": [
        548.3,
        183.1,
        649.0,
        256.9
      ],
      "is_dynamic": true,
      "mask_bbox_shape": [
        224,
        640
      ]
    },
    {
      "class_id": 2,
      "class_name": "car",
      "confidence": 0.6983,
      "bbox": [
        760.0,
        170.6,
        806.6,
        208.8
      ],
      "is_dynamic": true,
      "mask_bbox_shape": [
        224,
        640
      ]
    }
  ],
  "num_detections": 4,
  "num_dynamic": 4
}