{
  "frame_id": 372,
  "timestamp": 372.0,
  "image_path": "image_0/000372.png",
  "detections": [
    {
      "class_id": 2,
      "class_name": "car",
      "confidence": 0.8851,
      "bbox": [
        244.5,
        190.4,
        430.9,
        310.2
      ],
      "is_dynamic": true,
      "mask_bbox_shape": [
        224,
        640
      ]
    },
    {
      "class_id": 2,
      "class_name": "car",
      "confidence": 0.8415,
      "bbox": [
        414.2,
        187.4,
        490.4,
        237.3
      ],
      "is_dynamic": true,
      "mask_bbox_shape": [
        224,
        640
      ]
    },
    {
      "class_id": 2,
      "class_name": "car",
      "confidence": 0.4548,
      "bbox": [
        496.7,
        179.1,
        536.1,
        200.1
      ],
      "is_dynamic": true,
      "mask_bbox_shape": [
        224,
        640
      ]
    }
  ],
  "num_detections": 3,
  "num_dynamic": 3
}