{
  "frame_id": 1041,
  "timestamp": 1041.0,
  "image_path": "image_0/001041.png",
  "detections": [
    {
      "class_id": 2,
      "class_name": "car",
      "confidence": 0.933,
      "bbox": [
        1.3,
        199.9,
        432.7,
        373.0
      ],
      "is_dynamic": true,
      "mask_bbox_shape": [
        224,
        640
      ]
    },
    {
      "class_id": 2,
      "class_name": "car",
      "confidence": 0.8995,
      "bbox": [
        742.5,
        204.8,
        1175.8,
        373.6
      ],
      "is_dynamic": true,
      "mask_bbox_shape": [
        224,
        640
      ]
    },
    {
      "class_id": 2,
      "class_name": "car",
      "confidence": 0.8951,
      "bbox": [
        339.8,
        184.1,
        501.0,
        319.4
      ],
      "is_dynamic": true,
      "mask_bbox_shape": [
        224,
        640
      ]
    },
    {
      "class_id": 2,
      "class_name": "car",
      "confidence": 0.8537,
      "bbox": [
        478.7,
        178.7,
        561.7,
        242.7
      ],
      "is_dynamic": true,
      "mask_bbox_shape": [
        224,
        640
      ]
    }
  ],
  "num_detections": 4,
  "num_dynamic": 4
}