{
  "frame_id": 1218,
  "timestamp": 1218.0,
  "image_path": "image_0/001218.png",
  "detections": [
    {
      "class_id": 2,
      "class_name": "car",
      "confidence": 0.891,
      "bbox": [
        46.1,
        189.1,
        271.0,
        261.8
      ],
      "is_dynamic": true,
      "mask_bbox_shape": [
        224,
        640
      ]
    },
    {
      "class_id": 2,
      "class_name": "car",
      "confidence": 0.8906,
      "bbox": [
        321.7,
        196.0,
        506.5,
        266.9
      ],
      "is_dynamic": true,
      "mask_bbox_shape": [
        224,
        640
      ]
    },
    {
      "class_id": 2,
      "class_name": "car",
      "confidence": 0.8824,
      "bbox": [
        735.5,
        201.2,
        1019.1,
        345.8
      ],
      "is_dynamic": true,
      "mask_bbox_shape": [
        224,
        640
      ]
    },
    {
      "class_id": 2,
      "class_name": "car",
      "confidence": 0.4516,
      "bbox": [
        0.0,
        178.4,
        41.7,
        224.9
      ],
      "is_dynamic": true,
      "mask_bbox_shape": [
        224,
        640
      ]
    }
  ],
  "num_detections": 4,
  "num_dynamic": 4
}