{
  "frame_id": 2780,
  "timestamp": 2780.0,
  "image_path": "image_0/002780.png",
  "detections": [
    {
      "class_id": 2,
      "class_name": "car",
      "confidence": 0.9076,
      "bbox": [
        664.7,
        188.0,
        877.9,
        319.4
      ],
      "is_dynamic": true,
      "mask_bbox_shape": [
        224,
        640
      ]
    },
    {
      "class_id": 2,
      "class_name": "car",
      "confidence": 0.8319,
      "bbox": [
        853.9,
        217.1,
        1238.9,
        372.3
      ],
      "is_dynamic": true,
      "mask_bbox_shape": [
        224,
        640
      ]
    },
    {
      "class_id": 2,
      "class_name": "car",
      "confidence": 0.8261,
      "bbox": [
        333.8,
        195.3,
        464.0,
        291.5
      ],
      "is_dynamic": true,
      "mask_bbox_shape": [
        224,
        640
      ]
    },
    {
      "class_id": 2,
      "class_name": "car",
      "confidence": 0.6349,
      "bbox": [
        611.4,
        200.4,
        689.9,
        262.5
      ],
      "is_dynamic": true,
      "mask_bbox_shape": [
        224,
        640
      ]
    }
  ],
  "num_detections": 4,
  "num_dynamic": 4
}