{
  "frame_id": 3249,
  "timestamp": 3249.0,
  "image_path": "image_0/003249.png",
  "detections": [
    {
      "class_id": 2,
      "class_name": "car",
      "confidence": 0.8659,
      "bbox": [
        149.3,
        193.4,
        432.9,
        374.3
      ],
      "is_dynamic": true,
      "mask_bbox_shape": [
        224,
        640
      ]
    },
    {
      "class_id": 2,
      "class_name": "car",
      "confidence": 0.8458,
      "bbox": [
        745.3,
        179.8,
        914.7,
        319.6
      ],
      "is_dynamic": true,
      "mask_bbox_shape": [
        224,
        640
      ]
    },
    {
      "class_id": 2,
      "class_name": "car",
      "confidence": 0.7628,
      "bbox": [
        550.6,
        187.9,
        693.3,
        235.1
      ],
      "is_dynamic": true,
      "mask_bbox_shape": [
        224,
        640
      ]
    },
    {
      "class_id": 2,
      "class_name": "car",
      "confidence": 0.5,
      "bbox": [
        377.2,
        187.2,
        513.7,
        242.5
      ],
      "is_dynamic": true,
      "mask_bbox_shape": [
        224,
        640
      ]
    },
    {
      "class_id": 2,
      "class_name": "car",
      "confidence": 0.4567,
      "bbox": [
        900.7,
        182.4,
        986.1,
        237.0
      ],
      "is_dynamic": true,
      "mask_bbox_shape": [
        224,
        640
      ]
    }
  ],
  "num_detections": 5,
  "num_dynamic": 5
}