{
  "frame_id": 3610,
  "timestamp": 3610.0,
  "image_path": "image_0/003610.png",
  "detections": [
    {
      "class_id": 2,
      "class_name": "car",
      "confidence": 0.9071,
      "bbox": [
        750.6,
        196.5,
        965.3,
        331.2
      ],
      "is_dynamic": true,
      "mask_bbox_shape": [
        224,
        640
      ]
    },
    {
      "class_id": 2,
      "class_name": "car",
      "confidence": 0.7723,
      "bbox": [
        200.0,
        194.4,
        382.6,
        259.6
      ],
      "is_dynamic": true,
      "mask_bbox_shape": [
        224,
        640
      ]
    },
    {
      "class_id": 2,
      "class_name": "car",
      "confidence": 0.5093,
      "bbox": [
        674.3,
        187.3,
        739.5,
        247.9
      ],
      "is_dynamic": true,
      "mask_bbox_shape": [
        224,
        640
      ]
    }
  ],
  "num_detections": 3,
  "num_dynamic": 3
}