{
  "frame_id": 3899,
  "timestamp": 3899.0,
  "image_path": "image_0/003899.png",
  "detections": [
    {
      "class_id": 2,
      "class_name": "car",
      "confidence": 0.8845,
      "bbox": [
        1.0,
        225.9,
        142.4,
        371.6
      ],
      "is_dynamic": true,
      "mask_bbox_shape": [
        224,
        640
      ]
    },
    {
      "class_id": 2,
      "class_name": "car",
      "confidence": 0.805,
      "bbox": [
        364.0,
        177.7,
        462.2,
        253.7
      ],
      "is_dynamic": true,
      "mask_bbox_shape": [
        224,
        640
      ]
    },
    {
      "class_id": 2,
      "class_name": "car",
      "confidence": 0.6656,
      "bbox": [
        594.8,
        178.4,
        670.6,
        240.0
      ],
      "is_dynamic": true,
      "mask_bbox_shape": [
        224,
        640
      ]
    }
  ],
  "num_detections": 3,
  "num_dynamic": 3
}