{
  "frame_id": 388,
  "timestamp": 1341845701.633825,
  "image_path": "rgb/1341845701.633825.png",
  "detections": [
    {
      "class_id": 0,
      "class_name": "person",
      "confidence": 0.8896,
      "bbox": [
        41.8,
        127.3,
        248.0,
        460.5
      ],
      "is_dynamic": true,
      "mask_bbox_shape": [
        480,
        640
      ]
    },
    {
      "class_id": 62,
      "class_name": "tv",
      "confidence": 0.8824,
      "bbox": [
        352.9,
        163.1,
        486.5,
        262.2
      ],
      "is_dynamic": false,
      "mask_bbox_shape": [
        480,
        640
      ]
    },
    {
      "class_id": 0,
      "class_name": "person",
      "confidence": 0.8789,
      "bbox": [
        276.1,
        162.3,
        611.8,
        471.0
      ],
      "is_dynamic": true,
      "mask_bbox_shape": [
        480,
        640
      ]
    },
    {
      "class_id": 62,
      "class_name": "tv",
      "confidence": 0.8265,
      "bbox": [
        166.0,
        177.5,
        253.9,
        251.4
      ],
      "is_dynamic": false,
      "mask_bbox_shape": [
        480,
        640
      ]
    },
    {
      "class_id": 64,
      "class_name": "mouse",
      "confidence": 0.6686,
      "bbox": [
        255.8,
        278.1,
        273.1,
        291.3
      ],
      "is_dynamic": false,
      "mask_bbox_shape": [
        480,
        640
      ]
    }
  ],
  "num_detections": 5,
  "num_dynamic": 2
}